dynamus/__init__.py
dynamus/cli.py
dynamus-0.0.1.dist-info/licenses/LICENSE
dynamus-0.0.1.dist-info/METADATA
dynamus-0.0.1.dist-info/WHEEL
dynamus-0.0.1.dist-info/top_level.txt
dynamus-0.0.1.dist-info/RECORD
