Metadata-Version: 2.4
Name: dynamus
Version: 0.0.1
Summary: Ecosistema Dynamus para generación y orquestación modular de proyectos.
Author-email: Federico Monfasani <fmonfasani@gmail.com>
License-Expression: MIT
Classifier: Programming Language :: Python :: 3
Classifier: Operating System :: OS Independent
Requires-Python: >=3.9
License-File: LICENSE
Requires-Dist: dynamus-agent>=0.0.1
Requires-Dist: dynamus-core>=0.0.1
Requires-Dist: dynamus-backend>=0.0.1
Requires-Dist: dynamus-frontend>=0.0.1
Requires-Dist: dynamus-devops>=0.0.1
Requires-Dist: dynamus-cli>=0.0.1
Requires-Dist: dynamus-ai>=0.0.1
Requires-Dist: dynamus-templates>=0.0.1
Dynamic: license-file
